dummy.cpython-311-x86_64-linux-gnu.so
test/utils.py
test/tracked_markers_test.py
test/dce_instrumenter_test.py
test/instrumented_program_test.py
test/__init__.py
test/vr_instrumenter_test.py
test/preprocessing_test.py
test/dce_and_vr_instrument_test.py
test/serialization_test.py
program_markers-0.5.4.dist-info/METADATA
program_markers-0.5.4.dist-info/LICENSE
program_markers-0.5.4.dist-info/RECORD
program_markers-0.5.4.dist-info/WHEEL
program_markers-0.5.4.dist-info/top_level.txt
program_markers/__init__.py
program_markers/program-markers
program_markers/instrumenter.py
program_markers/py.typed
program_markers/markers.py
