Metadata-Version: 2.1
Name: program-markers
Version: 0.5.4
Summary: Inserts markers in C/C++ code. Markers expose information about the optimizations a compiler has applied, e.g., whether a piece of code was dead code eliminated.
Home-page: https://github.com/DeadCodeProductions/program-markers
Author: Theodoros Theodoridis
Author-email: theodort@inf.ethz.ch
License: Apache License 2.0
Classifier: Programming Language :: Python :: 3
Requires-Python: >=3.10
License-File: LICENSE
Requires-Dist: diopter >=0.0.26
